folder_selector/__init__.py
folder_selector/folder_selector.py
folder_selector/folder_selector_usage.py
folder_selector-0.1.5.dist-info/LICENSE
folder_selector-0.1.5.dist-info/METADATA
folder_selector-0.1.5.dist-info/WHEEL
folder_selector-0.1.5.dist-info/top_level.txt
folder_selector-0.1.5.dist-info/RECORD
